dephell_specifier/__init__.py
dephell_specifier/constants.py
dephell_specifier/git_specifier.py
dephell_specifier/range_specifier.py
dephell_specifier/specifier.py
dephell_specifier/utils.py
dephell_specifier-0.3.0.dist-info/LICENSE
dephell_specifier-0.3.0.dist-info/WHEEL
dephell_specifier-0.3.0.dist-info/METADATA
dephell_specifier-0.3.0.dist-info/RECORD
