Metadata-Version: 2.1
Name: dephell-specifier
Version: 0.3.0
Summary: A package to work with version specifiers.
Keywords: dephell,packaging,versioning,semver,version,maven
Author-email: Gram <git@orsinium.dev>
Requires-Python: >=3.7
Classifier: Development Status :: 4 - Beta
Classifier: Environment :: Console
Classifier: Intended Audience :: Developers
Classifier: License :: OSI Approved :: MIT License
Classifier: Programming Language :: Python
Classifier: Topic :: Software Development :: Libraries :: Python Modules
Classifier: Topic :: System :: Installation/Setup
Classifier: Programming Language :: Python :: 3.6
Classifier: Programming Language :: Python :: 3.7
Classifier: Programming Language :: Python :: 3.8
Classifier: Programming Language :: Python :: Implementation :: CPython
Classifier: Programming Language :: Python :: Implementation :: PyPy
Classifier: Operating System :: MacOS
Classifier: Operating System :: Microsoft :: Windows
Classifier: Operating System :: Unix
Requires-Dist: packaging
Requires-Dist: flake8 ; extra == "lint"
Requires-Dist: flake8-bugbear ; extra == "lint"
Requires-Dist: isort ; extra == "lint"
Requires-Dist: mypy ; extra == "lint"
Requires-Dist: unify ; extra == "lint"
Requires-Dist: pytest ; extra == "test"
Provides-Extra: lint
Provides-Extra: test
